CrackingCodesWithPythonZhongwenbanFix1/README.md
CrackingCodesWithPythonZhongwenbanFix1/__init__.py
CrackingCodesWithPythonZhongwenbanFix1/__main__.py
CrackingCodesWithPythonZhongwenbanFix1/file.epub
CrackingCodesWithPythonZhongwenbanFix1/index.html
CrackingCodesWithPythonZhongwenbanFix1/css/__init__.py
CrackingCodesWithPythonZhongwenbanFix1/css/annotations.css
CrackingCodesWithPythonZhongwenbanFix1/css/main.css
CrackingCodesWithPythonZhongwenbanFix1/css/normalize.css
CrackingCodesWithPythonZhongwenbanFix1/css/popup.css
CrackingCodesWithPythonZhongwenbanFix1/font/__init__.py
CrackingCodesWithPythonZhongwenbanFix1/font/fontello.eot
CrackingCodesWithPythonZhongwenbanFix1/font/fontello.svg
CrackingCodesWithPythonZhongwenbanFix1/font/fontello.ttf
CrackingCodesWithPythonZhongwenbanFix1/font/fontello.woff
CrackingCodesWithPythonZhongwenbanFix1/img/__init__.py
CrackingCodesWithPythonZhongwenbanFix1/img/annotator-glyph-sprite.png
CrackingCodesWithPythonZhongwenbanFix1/img/annotator-icon-sprite.png
CrackingCodesWithPythonZhongwenbanFix1/img/apple-touch-icon.png
CrackingCodesWithPythonZhongwenbanFix1/img/cancelfullscreen.png
CrackingCodesWithPythonZhongwenbanFix1/img/close.png
CrackingCodesWithPythonZhongwenbanFix1/img/fullscreen.png
CrackingCodesWithPythonZhongwenbanFix1/img/loader.gif
CrackingCodesWithPythonZhongwenbanFix1/img/menu-icon.png
CrackingCodesWithPythonZhongwenbanFix1/img/save.png
CrackingCodesWithPythonZhongwenbanFix1/img/saved.png
CrackingCodesWithPythonZhongwenbanFix1/img/settings-s.png
CrackingCodesWithPythonZhongwenbanFix1/img/settings.png
CrackingCodesWithPythonZhongwenbanFix1/img/star.png
CrackingCodesWithPythonZhongwenbanFix1/js/__init__.py
CrackingCodesWithPythonZhongwenbanFix1/js/epub.js
CrackingCodesWithPythonZhongwenbanFix1/js/epub.min.js
CrackingCodesWithPythonZhongwenbanFix1/js/epub.min.map
CrackingCodesWithPythonZhongwenbanFix1/js/hooks.min.js
CrackingCodesWithPythonZhongwenbanFix1/js/hooks.min.map
cracking_codes_with_python_zhongwenban_fix1-2025.3.25.0.dist-info/METADATA
cracking_codes_with_python_zhongwenban_fix1-2025.3.25.0.dist-info/WHEEL
cracking_codes_with_python_zhongwenban_fix1-2025.3.25.0.dist-info/entry_points.txt
cracking_codes_with_python_zhongwenban_fix1-2025.3.25.0.dist-info/top_level.txt
cracking_codes_with_python_zhongwenban_fix1-2025.3.25.0.dist-info/RECORD
